linux_do_mcp_steve/__init__.py
linux_do_mcp_steve/main.py
linux_do_mcp_steve-0.1.0.5.dist-info/METADATA
linux_do_mcp_steve-0.1.0.5.dist-info/WHEEL
linux_do_mcp_steve-0.1.0.5.dist-info/entry_points.txt
linux_do_mcp_steve-0.1.0.5.dist-info/RECORD
